bigcli/__init__.py
bigcli/bigcli.py
bigcli-0.2.0.dist-info/LICENSE
bigcli-0.2.0.dist-info/METADATA
bigcli-0.2.0.dist-info/WHEEL
bigcli-0.2.0.dist-info/top_level.txt
bigcli-0.2.0.dist-info/RECORD
