Metadata-Version: 2.1
Name: bigcli
Version: 0.2.0
Summary: A python framwork to write large CLIs using dependency injection
Home-page: https://github.com/dudadornelles/bigcli
Author: Duda Dornelles
Author-email: duda@thoughtworks.com
License: MIT license
Keywords: bigcli
Platform: UNKNOWN
Classifier: Development Status :: 2 - Pre-Alpha
Classifier: Intended Audience :: Developers
Classifier: License :: OSI Approved :: MIT License
Classifier: Natural Language :: English
Classifier: Programming Language :: Python :: 3.7
Requires-Dist: pinject
